py_async_grpc_prometheus/__init__.py
py_async_grpc_prometheus/client_metrics.py
py_async_grpc_prometheus/grpc_utils.py
py_async_grpc_prometheus/prometheus_async_client_interceptor.py
py_async_grpc_prometheus/prometheus_async_server_interceptor.py
py_async_grpc_prometheus/server_metrics.py
py_async_grpc_prometheus-0.2.0.dist-info/LICENSE
py_async_grpc_prometheus-0.2.0.dist-info/METADATA
py_async_grpc_prometheus-0.2.0.dist-info/WHEEL
py_async_grpc_prometheus-0.2.0.dist-info/top_level.txt
py_async_grpc_prometheus-0.2.0.dist-info/RECORD
