Metadata-Version: 2.1
Name: py_async_grpc_prometheus
Version: 0.2.0
Summary: Python async gRPC Prometheus Interceptors
Home-page: https://github.com/taranisag/py-async-grpc-prometheus
Author: Taranis
Author-email: avi.klaiman@taranis.com
License-File: LICENSE
Requires-Dist: setuptools>=39.0.1
Requires-Dist: grpcio>=1.10.0
Requires-Dist: prometheus_client>=0.3.0
